[
  {
    "icon": "",
    "title": "",
    "link": ""
  },
  {
    "icon": "images/2p.png",
    "title": "DeployGateのアプリ配信を操作するアプリをDeployGateで配信した話",
    "link": "https://qiita.com/bobu_web/private/eb1452d4cacb2e2c96e7"
  },
  {
    "icon": "images/sugo.jpeg",
    "title": "Netlifyで静的サイトのホスティングをする",
    "link": "https://qiita.com/sugo/items/2ee64887d682b0dae635"
  }, {
    "icon": "images/shinichi.png",
    "title": "ionicを業務レベルで使うとどうなるか",
    "link": "https://qiita.com/shinichi-takahashi/items/7d73dcd713ffbd46a56e"
  },
  {
    "icon": "images/2p.png",
    "title":
      "ionicプロジェクトでnodeの環境変数を使ってビルド環境を切り替えるのにちょっと面倒だった話",
    "link": "https://qiita.com/bobu_web/items/d908ae965ec587cdbe61"
  },
  {
    "icon": "images/sugo.jpeg",
    "title": "RailsからFCM(FirebaseCloudMessaging)を使ってみる<OAuth2.0利用>",
    "link": "https://qiita.com/sugo/items/63d55ff8d3802dae70bc"
  },
  {
    "icon": "",
    "title": "",
    "link": ""
  },
  {
    "icon": "",
    "title": "",
    "link": ""
  },
  {
    "icon": "images/2p.png",
    "title": "逆引きLuxon集　〜moment.jsから乗り換えるために〜",
    "link": "https://qiita.com/bobu_web/items/2cecc3fdb7d2b0942ef1"
  },
  {
    "icon": "images/shinichi.png",
    "title":
      "AWS Lambda利用を前提にフレームワークを選ぶときに僕がかんがえたこと",
    "link": "https://qiita.com/shinichi-takahashi/items/1a3da4158d7d5ff48f2b"
  },
  {
    "icon": "images/takunosuke.jpg",
    "title": "IT業界で働いてみた10日目の雑感（タスク管理について）",
    "link": "https://qiita.com/Takunosuke/items/8747863b881e8e6a8dc5"
  },
  {
    "icon": "images/2p.png",
    "title": "DeployGateの配布ページを使ってリンク共有のみでアプリ配信する",
    "link": "https://qiita.com/bobu_web/items/38478a5d5a30b246cfc8"
  },
  {
    "icon": "images/on3.png",
    "title": "PingFederateを使ってSAML認証対応してみた",
    "link": "https://qiita.com/daiki-onda/items/5e66c0299419bf8b27d5"
  },
  {
    "icon": "",
    "title": "",
    "link": ""
  },
  {
    "icon": "",
    "title": "",
    "link": ""
  },
  {
    "icon": "images/2p.png",
    "title": "Vue.jsでビューの変更がされないときに疑うこと+主な解決策方法",
    "link": "https://qiita.com/bobu_web/items/ec5a98d03758d12ad721"
  },
  {
    "icon": "images/kai.jpg",
    "title": "5分でできるMacBook Proに最低限の開発環境構築",
    "link": "https://qiita.com/kai_kou/items/3107e0a056c7a1b569cd"
  },
  {
    "icon": "images/kai.jpg",
    "title": "Macでanyenvをつかってpython環境構築(bash、fish対応)",
    "link": "https://qiita.com/kai_kou/items/f54931991a781b96bb9c"
  },
  {
    "icon": "images/kai.jpg",
    "title": "Macでhomebrewを使ってUnityをインストールする(Unity Hub、日本語化対応)",
    "link": "https://qiita.com/kai_kou/items/445e614fb71f2204e033"
  },
  {
    "icon": "images/shinichi.png",
    "title": "TypeORMのリレーション定義に気をつけよう。死ぬぞ。",
    "link": "https://qiita.com/shinichi-takahashi/items/e47d869fb83fb27fae91"
  },
  {
    "icon": "",
    "title": "",
    "link": ""
  },
  {
    "icon": "",
    "title": "",
    "link": ""
  },
  {
    "icon": "images/kai.jpg",
    "title": "MacでUnity ML-Agentsの環境を構築する",
    "link": "https://qiita.com/kai_kou/items/6478fa686ce1af5939d8"
  },
  {
    "icon": "images/shinichi.png",
    "title": "TypeORM+ServerlessFrameworkでおのれwebpackなmysqlエラー",
    "link": "https://qiita.com/shinichi-takahashi/items/738c3c9065c67c4bef3c"
  },
  {
    "icon": "images/koruri.jpg",
    "title": "JSON Schema で快適に CloudFormation テンプレートを書く",
    "link": "https://qiita.com/y13i/items/6b6e9698764a29fc8f0a"
  },
  {
    "icon": "",
    "title": "",
    "link": ""
  },
  {
    "icon": "",
    "title": "",
    "link": ""
  },
  {
    "icon": "",
    "title": "",
    "link": ""
  },
  {
    "icon": "",
    "title": "",
    "link": ""
  },
  {
    "icon": "",
    "title": "",
    "link": ""
  },
  {
    "icon": "",
    "title": "",
    "link": ""
  }
]
